{
  "tasks": [
    {
      "id": "TASK-001",
      "title": "Инициализация репозитория",
      "status": "completed",
      "file": "TASK-001-init-repository.md",
      "createdDate": null,
      "completedDate": null,
      "branch": null
    },
    {
      "id": "TASK-002",
      "title": "Инициализация Backend проекта на Fastify",
      "status": "completed",
      "file": "TASK-002-init-be-project.md",
      "createdDate": "2026-01-27T10:00:00Z",
      "completedDate": "2026-01-28T00:00:00Z",
      "branch": "feature/TASK-002-init-be-project"
    },
    {
      "id": "TASK-003",
      "title": "Реализация API для формы отчётности 6406",
      "status": "completed",
      "file": "TASK-003-implement-6406-report-api.md",
      "createdDate": "2026-01-28T00:00:00Z",
      "completedDate": "2026-01-28T15:00:00Z",
      "branch": "feature/TASK-003-implement-6406-report-api"
    },
    {
      "id": "TASK-004",
      "title": "Создание Task Viewer приложения",
      "status": "completed",
      "file": "TASK-004-create-task-viewer.md",
      "createdDate": "2026-01-28T12:00:00Z",
      "completedDate": null,
      "branch": null
    },
    {
      "id": "TASK-005",
      "title": "Добавление новой функциональности в API формы 6406",
      "status": "completed",
      "file": "TASK-005-extend-6406-api-universal-report.md",
      "createdDate": "2026-01-28T14:00:00Z",
      "completedDate": "2026-01-29T00:00:00Z",
      "branch": "feature/TASK-005-extend-6406-api"
    },
    {
      "id": "TASK-006",
      "title": "Исправление отображения схем в Swagger документации",
      "status": "completed",
      "file": "TASK-006-fix-swagger-schemas-display.md",
      "createdDate": "2026-01-28T16:00:00Z",
      "completedDate": "2026-01-29T10:00:00Z",
      "branch": "feature/TASK-006-fix-swagger-schemas"
    },
    {
      "id": "TASK-007",
      "title": "Рефакторинг структуры API для формы 6406",
      "status": "completed",
      "file": "TASK-007-refactor-api-structure.md",
      "createdDate": "2026-01-29T00:00:00Z",
      "completedDate": "2026-01-29T12:00:00Z",
      "branch": "feature/TASK-007-refactor-api"
    },
    {
      "id": "TASK-008",
      "title": "Стандартизация хранения и передачи размеров файлов и пакетов",
      "status": "completed",
      "file": "TASK-008-standardize-size-storage-and-api.md",
      "createdDate": "2026-01-29T14:00:00Z",
      "completedDate": "2026-01-29T18:00:00Z",
      "branch": "task-008-standardize-size-storage-and-api"
    },
    {
      "id": "TASK-009",
      "title": "Настройка GitHub Actions и GitHub Pages для публикации Swagger документации",
      "status": "completed",
      "file": "TASK-009-setup-github-actions-and-pages.md",
      "createdDate": "2026-01-29T16:00:00Z",
      "completedDate": "2026-01-29T20:00:00Z",
      "branch": "feature/TASK-009-setup-github-actions"
    }
  ]
}